{
    "predicate": {
        "glow_intensity": 0.8732610909090909,
        "spatial_coordinate": {
            "node_id": "NODE_2_6",
            "recursion_depth": 6,
            "coordinates": [
                0.518,
                0.716,
                -0.45799999999999996,
                0.968,
                0.6100000000000001,
                -0.5700000000000001,
                0.1399999999999999,
                0.5760000000000001,
                0.23199999999999998,
                -0.46599999999999997,
                0.514,
                0.5840000000000001,
                -0.796,
                -0.954,
                0.476,
                -0.55,
                0.21799999999999997,
                0.742
            ],
            "adjacency_value": 0.0
        },
        "epistemic_alignment": 0.6912499999999999,
        "deterministic": false,
        "predictive_intent": {},
        "jump_vector": [],
        "cognitive_mode": "GUARD",
        "bayes_habit_prob": 5.257767150935973e-48,
        "bayes_jump_prob": 4.560853402996719e-37,
        "bayes_guard_prob": 0.9888496589668324,
        "epistemic_bayes": {
            "locke": 5.305528267410477e-12,
            "hume": 4.653700445967061e-14,
            "kant": 8.99481136504513e-13,
            "spinoza": 1.0093168067500401e-12
        }
    },
    "confidence": 0.8732610909090909,
    "triad_c_mode": "GUARD",
    "field_density": 91
}