{
    "predicate": {
        "glow_intensity": 0.8721854545454545,
        "spatial_coordinate": {
            "node_id": "NODE_3_2",
            "recursion_depth": 2,
            "coordinates": [
                0.42599999999999993,
                -0.8160000000000001,
                0.6200000000000001,
                0.22199999999999998,
                0.6639999999999999,
                -0.626,
                0.748,
                -0.394,
                0.956,
                -0.06999999999999995,
                0.29600000000000004,
                0.736,
                -0.42200000000000004,
                0.45599999999999996,
                -0.43799999999999994,
                -0.20199999999999996,
                0.44799999999999995,
                -0.902
            ],
            "adjacency_value": 0.0
        },
        "epistemic_alignment": 0.7397499999999999,
        "deterministic": false,
        "predictive_intent": {},
        "jump_vector": [],
        "cognitive_mode": "GUARD",
        "bayes_habit_prob": 1.3781089763028328e-15,
        "bayes_jump_prob": 2.1445029108654294e-12,
        "bayes_guard_prob": 0.9631314591780157,
        "epistemic_bayes": {
            "locke": 4.5768181238863957e-05,
            "hume": 0.00019543093563994412,
            "kant": 2.2805952361494235e-05,
            "spinoza": 0.00015712273393530415
        }
    },
    "confidence": 0.8721854545454545,
    "triad_c_mode": "GUARD",
    "field_density": 29
}